{
  "categorias": [
    {
      "titulo": "Filmes",
      "cor": "red",
      "videos": [
        {
          "titulo": "Interestelar",
          "url": "https://www.youtube.com/watch?v=mbbPSq63yuM"
        },
        {
          "titulo": "Guerra dos Mundos",
          "url": "https://www.youtube.com/watch?v=uGR9Jrk1cws"
        },
        {
          "titulo": "Star Wars IV",
          "url": "https://www.youtube.com/watch?v=vZ734NWnAHA"
        },
        {
          "titulo": "Star Wars V",
          "url": "https://www.youtube.com/watch?v=JNwNXF9Y6kY"
        },
        {
          "titulo": "Star Wars VII",
          "url": "https://www.youtube.com/watch?v=sGbxmsDFVnE"
        },
        {
          "titulo": "Os Incríveis",
          "url": "https://www.youtube.com/watch?v=P7KMDFpqXqk"
        },
        {
          "titulo": "Logan",
          "url": "https://www.youtube.com/watch?v=KPND6SgkN7Q"
        }
      ]
    },
    {
      "titulo": "Séries",
      "cor": "red",
      "videos": [
        {
          "titulo": "Dark",
          "url": "https://www.youtube.com/watch?v=ESEUoa-mz2c"
        },
        {
          "titulo": "Sword Art Online",
          "url": "https://www.youtube.com/watch?v=6ohYYtxfDCg"
        },
        {
          "titulo": "Westworld",
          "url": "https://www.youtube.com/watch?v=jBfOlQrko0c"
        },
        {
          "titulo": "Como vender drogas online (rápido)",
          "url": "https://www.youtube.com/watch?v=jwiCmA5vX-A"
        },
        {
          "titulo": "Chernobyl",
          "url": "https://www.youtube.com/watch?v=s9APLXM9Ei8"
        }
      ]
    },
    {
      "titulo": "Games",
      "cor": "red",
      "videos": [
        {
          "titulo": "Battlefield 4",
          "url": "https://www.youtube.com/watch?v=wJ_F525yHVY"
        },
        {
          "titulo": "Portal 2",
          "url": "https://www.youtube.com/watch?v=tax4e4hBBZc"
        },
        {
          "titulo": "FIFA 15",
          "url": "https://www.youtube.com/watch?v=TnTYVT6lwBc"
        },
        {
          "titulo": "Tom Clancy's Rainbow Six Siege",
          "url": "https://www.youtube.com/watch?v=JSapXD9vxYA"
        },
        {
          "titulo": "Call of Duty: Black Ops 2",
          "url": "https://www.youtube.com/watch?v=x3tedlWs1XY"
        },
        {
          "titulo": "Far Cry 4",
          "url": "https://www.youtube.com/watch?v=6d60v1OErEY"
        }
      ]
    },
    {
      "titulo": "Músicas",
      "cor": "red",
      "videos": [
        {
          "titulo": "The Black Eyed Peas - I Gotta Feeling",
          "url": "https://www.youtube.com/watch?v=uSD4vsh1zDA"
        },
        {
          "titulo": "Imagine Dragons - Believer",
          "url": "https://www.youtube.com/watch?v=7wtfhZwyrcc"
        },
        {
          "titulo": "AC/DC - Highway to Hell",
          "url": "https://www.youtube.com/watch?v=l482T0yNkeo"
        },
        {
          "titulo": "Bon Jovi - It's My Life",
          "url": "https://www.youtube.com/watch?v=vx2u5uUu3DE"
        }, 
        {
          "titulo": "Nando Reis - Pra Você Guardei O Amor",
          "url": "https://www.youtube.com/watch?v=aUzW9io-Om0"
        },
        {
          "titulo": "Imagine Dragons - Thunder",
          "url": "https://www.youtube.com/watch?v=fKopy74weus"
        },
        {
          "titulo": "Skank - É Uma Partida De Futebol",
          "url": "https://www.youtube.com/watch?v=7Ie4oL17Nwc"
        }
      ]
    }
  ]
}